demogua/__init__.py
demogua-1.0.dist-info/METADATA
demogua-1.0.dist-info/WHEEL
demogua-1.0.dist-info/top_level.txt
demogua-1.0.dist-info/RECORD
