Metadata-Version: 2.1
Name: demogua
Version: 1.0
Summary: This is a test of the setup
Home-page: https://www.baidu.com
Author: cccc
Author-email: cccc@cccc.com
License: UNKNOWN
Platform: UNKNOWN
